py_etherpad/__init__.py
pyetherpadlite-1.2.dist-info/METADATA
pyetherpadlite-1.2.dist-info/WHEEL
pyetherpadlite-1.2.dist-info/top_level.txt
pyetherpadlite-1.2.dist-info/zip-safe
pyetherpadlite-1.2.dist-info/RECORD
