Metadata-Version: 2.1
Name: pyetherpadlite
Version: 1.2
Summary: Python bindings for Etherpad's HTTP API. (https://github.com/ether/etherpad-lite)
Home-page: https://github.com/Alienmaster/PyEtherpadLite
Author: alienmaster, devjones
Author-email: github@crpykng.de
License: Apache Software License 2.0
Project-URL: Bug Tracker, https://github.com/Alienmaster/PyEtherpadLite/issues
Project-URL: Source Code, https://github.com/Alienmaster/PyEtherpadLite
Platform: any
